coomer/__init__.py
coomer/asyncio.py
coomer/creator.py
coomer/parser.py
coomer/post.py
coomer/utils.py
coomer-0.1.2.dist-info/METADATA
coomer-0.1.2.dist-info/WHEEL
coomer-0.1.2.dist-info/top_level.txt
coomer-0.1.2.dist-info/RECORD
