Metadata-Version: 2.1
Name: coomer
Version: 0.1.2
Summary: Coomer/Kemono Api client
Home-page: https://github.com/sero01000/coomer
Author: sero01000
Author-email: author@example.com
License: MIT
Keywords: coomer,kemono,api,asyncio
Classifier: License :: OSI Approved :: MIT License
Classifier: Operating System :: OS Independent
Classifier: Programming Language :: Python :: 3.9
Classifier: Programming Language :: Python :: 3.10
Classifier: Programming Language :: Python :: 3.11
Classifier: Programming Language :: Python :: 3.12
Classifier: Programming Language :: Python :: 3.13
Requires-Python: >=3.9
Requires-Dist: pydantic <2.11,>=2.4.1
Requires-Dist: requests <3.0.0,>=2.0.0
Provides-Extra: aiohttp
Requires-Dist: aiohttp <3.12,>=3.9.0 ; extra == 'aiohttp'
